deckr/hw/__init__.py
deckr/hw/events.py
deckr/plugin/__init__.py
deckr/plugin/events.py
deckr-0.0.0.dist-info/LICENSE
deckr-0.0.0.dist-info/METADATA
deckr-0.0.0.dist-info/WHEEL
deckr-0.0.0.dist-info/RECORD
