Metadata-Version: 2.3
Name: deckr
Version: 0.0.0
Summary: A Pyodide-based library for controlling multiple 'dock' devices
License: MIT
Author: Kaj Siebert
Author-email: kaj@k-si.com
Requires-Python: >=3.11
Classifier: Development Status :: 3 - Alpha
Classifier: Intended Audience :: Developers
Classifier: License :: OSI Approved :: MIT License
Classifier: Operating System :: OS Independent
Classifier: Programming Language :: Python :: 3
Classifier: Programming Language :: Python :: 3.11
Classifier: Programming Language :: Python :: 3.12
Classifier: Topic :: Multimedia
Classifier: Topic :: System :: Hardware
Requires-Dist: pydantic (>=2.12.5,<3.0.0)
Project-URL: Repository, https://github.com/kws/deckr.git
